alpha_viewer/__init__.py
alpha_viewer-0.1.5.dist-info/LICENSE
alpha_viewer-0.1.5.dist-info/WHEEL
alpha_viewer-0.1.5.dist-info/METADATA
alpha_viewer-0.1.5.dist-info/RECORD
