Metadata-Version: 2.1
Name: alpha_viewer
Version: 0.1.5
Summary: Alphafold Protein model viewer
Author: Severin Dicks
Requires-Python: >=3.8
Requires-Dist: numpy>=1.9.0
Requires-Dist: pandas>=1.3.0
Requires-Dist: py3Dmol>=1.8.0
Requires-Dist: ipywidgets>=7.5.0
Requires-Dist: matplotlib>=3.5.0
Project-URL: Source, https://github.com/Intron7/alpha_viewer
